tessng/TESSNG.exe
tessng/TESSNG_en_US.qm
tessng/TESS_DB.dll
tessng/TESS_MODEL.dll
tessng/TESS_NET.dll
tessng/TESS_SIMU.dll
tessng/TESS_WIN.dll
tessng/TessChart.dll
tessng/TessInterfaces.dll
tessng/TessSupport.dll
tessng/Tessng.pyd
tessng/__init__.py
tessng/__init__.pyi
tessng/assimp-vc143-mt.dll
tessng/fmt.dll
tessng/freetype.dll
tessng/jpeg62.dll
tessng/libEGL.dll
tessng/libEGLd.dll
tessng/libGLESv2.dll
tessng/libGLESv2d.dll
tessng/libPythonPanel.dll
tessng/libcrypto-3-x64.dll
tessng/libcurl.dll
tessng/liblzma.dll
tessng/libprotobuf.dll
tessng/libssl-3-x64.dll
tessng/lz4.dll
tessng/metis.dll
tessng/msvcp140.dll
tessng/opengl32sw.dll
tessng/openglrenderer.dll
tessng/proj.dll
tessng/shiboken2.abi3.dll
tessng/spdlog.dll
tessng/sqlite3.dll
tessng/tiff.dll
tessng/zlib1.dll
tessng-4.1.0.2.dist-info/LICENSE
tessng-4.1.0.2.dist-info/METADATA
tessng-4.1.0.2.dist-info/WHEEL
tessng-4.1.0.2.dist-info/top_level.txt
tessng-4.1.0.2.dist-info/RECORD
