Metadata-Version: 2.1
Name: tessng
Version: 4.1.0.2
Summary: TESS NG 4.1 Secondary Development (Python Version)
Home-page: http://jidatraffic.com:82/
Author: Jida Transportation
Author-email: 948117072@qq.com
License: MIT
Platform: UNKNOWN
Classifier: License :: OSI Approved :: MIT License
Classifier: Programming Language :: Python :: 3.6
Classifier: Operating System :: Microsoft :: Windows
Classifier: Topic :: Education :: Computer Aided Instruction (CAI)
Classifier: Topic :: Games/Entertainment :: Simulation
Classifier: Topic :: Software Development :: Libraries :: Python Modules
Requires-Python: ==3.6.*
License-File: LICENSE
Requires-Dist: shiboken2
Requires-Dist: PySide2 (>=5.15.2)
